py_fast_rsync-0.1.0.dist-info/METADATA
py_fast_rsync-0.1.0.dist-info/WHEEL
py_fast_rsync/signature.pyi
py_fast_rsync/py_fast_rsync.pyi
py_fast_rsync/__init__.py
py_fast_rsync/py_fast_rsync.cpython-39-powerpc64le-linux-gnu.so
py_fast_rsync-0.1.0.dist-info/RECORD
